yatl/__init__.py
yatl/interpolation.py
yatl/render.py
yatl/types.py
pyyatl-0.7.0.dist-info/LICENSE
pyyatl-0.7.0.dist-info/WHEEL
pyyatl-0.7.0.dist-info/METADATA
pyyatl-0.7.0.dist-info/RECORD
