Metadata-Version: 2.1
Name: pyyatl
Version: 0.7.0
Summary: YAML Templating Language
Home-page: https://github.com/d5h-foss/yatl
License: MIT
Keywords: yaml,template
Author: Dan Hipschman
Requires-Python: >=3.6,<4.0
Classifier: License :: OSI Approved :: MIT License
Classifier: Programming Language :: Python :: 3
Classifier: Programming Language :: Python :: 3.6
Classifier: Programming Language :: Python :: 3.7
Classifier: Programming Language :: Python :: 3.8
Requires-Dist: pyyaml (>=5.3.1,<6.0.0)
Project-URL: Documentation, https://yatl.readthedocs.io
Project-URL: Repository, https://github.com/d5h-foss/yatl
